{
  "main": {
    "id": "9b22d4deb71eb940",
    "type": "split",
    "children": [
      {
        "id": "698dbd554313b4ed",
        "type": "tabs",
        "children": [
          {
            "id": "be81c70e4ec042b9",
            "type": "leaf",
            "state": {
              "type": "empty",
              "state": {},
              "icon": "lucide-file",
              "title": "New tab"
            }
          }
        ]
      }
    ],
    "direction": "vertical"
  },
  "left": {
    "id": "8c7c6abfa42b66eb",
    "type": "split",
    "children": [
      {
        "id": "8dbda3521b73d04e",
        "type": "tabs",
        "children": [
          {
            "id": "5f1954ac2e033dbd",
            "type": "leaf",
            "state": {
              "type": "file-explorer",
              "state": {
                "sortOrder": "alphabetical",
                "autoReveal": false
              },
              "icon": "lucide-folder-closed",
              "title": "Files"
            }
          },
          {
            "id": "861a6be7937d67d6",
            "type": "leaf",
            "state": {
              "type": "search",
              "state": {
                "query": "",
                "matchingCase": false,
                "explainSearch": false,
                "collapseAll": false,
                "extraContext": false,
                "sortOrder": "alphabetical"
              },
              "icon": "lucide-search",
              "title": "Search"
            }
          },
          {
            "id": "98af6f7aaa7f77ea",
            "type": "leaf",
            "state": {
              "type": "bookmarks",
              "state": {},
              "icon": "lucide-bookmark",
              "title": "Bookmarks"
            }
          }
        ]
      }
    ],
    "direction": "horizontal",
    "width": 300
  },
  "right": {
    "id": "0e662bb00758b344",
    "type": "split",
    "children": [
      {
        "id": "49f5862359bb36a0",
        "type": "tabs",
        "children": [
          {
            "id": "31874dc21ef13509",
            "type": "leaf",
            "state": {
              "type": "backlink",
              "state": {
                "file": "Theme.md",
                "collapseAll": false,
                "extraContext": false,
                "sortOrder": "alphabetical",
                "showSearch": false,
                "searchQuery": "",
                "backlinkCollapsed": false,
                "unlinkedCollapsed": true
              },
              "icon": "links-coming-in",
              "title": "Backlinks for Theme"
            }
          },
          {
            "id": "d61e389ff5c415cd",
            "type": "leaf",
            "state": {
              "type": "outgoing-link",
              "state": {
                "file": "Theme.md",
                "linksCollapsed": false,
                "unlinkedCollapsed": true
              },
              "icon": "links-going-out",
              "title": "Outgoing links from Theme"
            }
          },
          {
            "id": "266c6287dd25c415",
            "type": "leaf",
            "state": {
              "type": "tag",
              "state": {
                "sortOrder": "frequency",
                "useHierarchy": true,
                "showSearch": false,
                "searchQuery": ""
              },
              "icon": "lucide-tags",
              "title": "Tags"
            }
          },
          {
            "id": "98bc1296d3f7c869",
            "type": "leaf",
            "state": {
              "type": "all-properties",
              "state": {
                "sortOrder": "frequency",
                "showSearch": false,
                "searchQuery": ""
              },
              "icon": "lucide-archive",
              "title": "All properties"
            }
          },
          {
            "id": "9f07152dde5703a5",
            "type": "leaf",
            "state": {
              "type": "outline",
              "state": {
                "file": "Theme.md",
                "followCursor": false,
                "showSearch": false,
                "searchQuery": ""
              },
              "icon": "lucide-list",
              "title": "Outline of Theme"
            }
          }
        ]
      }
    ],
    "direction": "horizontal",
    "width": 300,
    "collapsed": true
  },
  "left-ribbon": {
    "hiddenItems": {
      "switcher:Open quick switcher": false,
      "graph:Open graph view": false,
      "canvas:Create new canvas": false,
      "daily-notes:Open today's daily note": false,
      "templates:Insert template": false,
      "command-palette:Open command palette": false,
      "bases:Create new base": false
    }
  },
  "active": "be81c70e4ec042b9",
  "lastOpenFiles": [
    "Theme.md",
    "Chức năng.md",
    "Untitled.canvas",
    "AMP.md",
    "img/Pasted image 20260127190323.png",
    "img",
    "img/Pasted image 20260127192737.png",
    "img/Pasted image 20260127192017.png",
    "img/Pasted image 20260127191920.png",
    "img/Pasted image 20260127191633.png",
    "img/Pasted image 20260127191356.png",
    "img/Pasted image 20260127191303.png",
    "img/Pasted image 20260127191254.png"
  ]
}